{
  "efficientnet_best_reference_07186": {
    "backbone": "efficientnet_b0_bilstm",
    "backend": "frames",
    "epochs": 12,
    "frame_step": 2,
    "pos_sample_prob": 0.1,
    "grad_accum_steps": 4,
    "grad_clip": 1.0,
    "label_smoothing": 0.0,
    "class_weight_pos_mult": 1.15,
    "base_lr": 8e-05,
    "backbone_lr_mult": 0.2,
    "adamw_weight_decay": 0.0005,
    "onecycle_peak_mult": 6.0,
    "onecycle_pct_start": 0.25,
    "onecycle_div_factor": 25.0,
    "onecycle_final_div": 10000.0,
    "auto_load_best_after_train": true,
    "use_trivial_aug_wide": true,
    "trivial_aug_num_magnitude_bins": 31,
    "strong_aug": false,
    "temporal_coherent_aug": false,
    "enable_cb_loss": false,
    "layer_decay": 1.0
  },
  "r3d_18_v2_conservative": {
    "backbone": "r3d_18_temporal_v2",
    "backend": "frames",
    "auto_load_best_after_train": true,
    "adamw_weight_decay": 0.0005,
    "grad_clip": 1.0,
    "onecycle_div_factor": 25.0,
    "onecycle_final_div": 10000.0,
    "enable_cb_loss": false,
    "bilstm_hidden": 256,
    "bilstm_layers": 2,
    "use_trivial_aug_wide": false,
    "strong_aug": false,
    "temporal_coherent_aug": true,
    "tc_aug_scale_min": 0.75,
    "tc_aug_color_jitter": 0.1,
    "tc_aug_hflip_prob": 0.5,
    "tc_aug_erasing_prob": 0.1,
    "frame_step": 1,
    "epochs": 20,
    "base_lr": 5e-05,
    "backbone_lr_mult": 0.1,
    "onecycle_peak_mult": 5.0,
    "onecycle_pct_start": 0.25,
    "pos_sample_prob": 0.1,
    "class_weight_pos_mult": 1.15,
    "label_smoothing": 0.02,
    "grad_accum_steps": 4,
    "train_batch_size": 4,
    "val_batch_size": 4,
    "val_clip_mode": "random",
    "val_n_views": 11
  },
  "r3d_18_v2_push": {
    "backbone": "r3d_18_temporal_v2",
    "backend": "frames",
    "auto_load_best_after_train": true,
    "adamw_weight_decay": 0.0005,
    "grad_clip": 1.0,
    "onecycle_div_factor": 25.0,
    "onecycle_final_div": 10000.0,
    "enable_cb_loss": false,
    "bilstm_hidden": 256,
    "bilstm_layers": 2,
    "use_trivial_aug_wide": false,
    "strong_aug": false,
    "temporal_coherent_aug": true,
    "tc_aug_scale_min": 0.75,
    "tc_aug_color_jitter": 0.1,
    "tc_aug_hflip_prob": 0.5,
    "tc_aug_erasing_prob": 0.1,
    "frame_step": 1,
    "epochs": 25,
    "base_lr": 6e-05,
    "backbone_lr_mult": 0.15,
    "onecycle_peak_mult": 6.0,
    "onecycle_pct_start": 0.3,
    "pos_sample_prob": 0.15,
    "class_weight_pos_mult": 1.2,
    "label_smoothing": 0.01,
    "grad_accum_steps": 4,
    "train_batch_size": 4,
    "val_batch_size": 4,
    "val_clip_mode": "random",
    "val_n_views": 11
  },
  "r2plus1d_18_v2_conservative": {
    "backbone": "r2plus1d_18_temporal_v2",
    "backend": "frames",
    "auto_load_best_after_train": true,
    "adamw_weight_decay": 0.0005,
    "grad_clip": 1.0,
    "onecycle_div_factor": 25.0,
    "onecycle_final_div": 10000.0,
    "enable_cb_loss": false,
    "bilstm_hidden": 256,
    "bilstm_layers": 2,
    "use_trivial_aug_wide": false,
    "strong_aug": false,
    "temporal_coherent_aug": true,
    "tc_aug_scale_min": 0.75,
    "tc_aug_color_jitter": 0.1,
    "tc_aug_hflip_prob": 0.5,
    "tc_aug_erasing_prob": 0.1,
    "frame_step": 1,
    "epochs": 20,
    "base_lr": 5e-05,
    "backbone_lr_mult": 0.1,
    "onecycle_peak_mult": 5.0,
    "onecycle_pct_start": 0.25,
    "pos_sample_prob": 0.1,
    "class_weight_pos_mult": 1.15,
    "label_smoothing": 0.02,
    "grad_accum_steps": 4,
    "train_batch_size": 4,
    "val_batch_size": 4,
    "val_clip_mode": "random",
    "val_n_views": 11
  },
  "r2plus1d_18_v2_push": {
    "backbone": "r2plus1d_18_temporal_v2",
    "backend": "frames",
    "auto_load_best_after_train": true,
    "adamw_weight_decay": 0.0005,
    "grad_clip": 1.0,
    "onecycle_div_factor": 25.0,
    "onecycle_final_div": 10000.0,
    "enable_cb_loss": false,
    "bilstm_hidden": 256,
    "bilstm_layers": 2,
    "use_trivial_aug_wide": false,
    "strong_aug": false,
    "temporal_coherent_aug": true,
    "tc_aug_scale_min": 0.75,
    "tc_aug_color_jitter": 0.1,
    "tc_aug_hflip_prob": 0.5,
    "tc_aug_erasing_prob": 0.1,
    "frame_step": 1,
    "epochs": 25,
    "base_lr": 7e-05,
    "backbone_lr_mult": 0.15,
    "onecycle_peak_mult": 6.0,
    "onecycle_pct_start": 0.3,
    "pos_sample_prob": 0.15,
    "class_weight_pos_mult": 1.2,
    "label_smoothing": 0.01,
    "grad_accum_steps": 4,
    "train_batch_size": 4,
    "val_batch_size": 4,
    "val_clip_mode": "random",
    "val_n_views": 11
  },
  "s3d_v2_conservative": {
    "backbone": "s3d_temporal_v2",
    "backend": "frames",
    "auto_load_best_after_train": true,
    "adamw_weight_decay": 0.0005,
    "grad_clip": 1.0,
    "onecycle_div_factor": 25.0,
    "onecycle_final_div": 10000.0,
    "enable_cb_loss": false,
    "bilstm_hidden": 256,
    "bilstm_layers": 2,
    "use_trivial_aug_wide": false,
    "strong_aug": false,
    "temporal_coherent_aug": true,
    "tc_aug_scale_min": 0.75,
    "tc_aug_color_jitter": 0.1,
    "tc_aug_hflip_prob": 0.5,
    "tc_aug_erasing_prob": 0.1,
    "frame_step": 1,
    "epochs": 20,
    "base_lr": 5e-05,
    "backbone_lr_mult": 0.1,
    "onecycle_peak_mult": 5.0,
    "onecycle_pct_start": 0.25,
    "pos_sample_prob": 0.1,
    "class_weight_pos_mult": 1.15,
    "label_smoothing": 0.02,
    "grad_accum_steps": 4,
    "train_batch_size": 4,
    "val_batch_size": 4,
    "val_clip_mode": "random",
    "val_n_views": 11
  },
  "s3d_v2_push": {
    "backbone": "s3d_temporal_v2",
    "backend": "frames",
    "auto_load_best_after_train": true,
    "adamw_weight_decay": 0.0005,
    "grad_clip": 1.0,
    "onecycle_div_factor": 25.0,
    "onecycle_final_div": 10000.0,
    "enable_cb_loss": false,
    "bilstm_hidden": 256,
    "bilstm_layers": 2,
    "use_trivial_aug_wide": false,
    "strong_aug": false,
    "temporal_coherent_aug": true,
    "tc_aug_scale_min": 0.75,
    "tc_aug_color_jitter": 0.1,
    "tc_aug_hflip_prob": 0.5,
    "tc_aug_erasing_prob": 0.1,
    "frame_step": 1,
    "epochs": 25,
    "base_lr": 6e-05,
    "backbone_lr_mult": 0.15,
    "onecycle_peak_mult": 6.0,
    "onecycle_pct_start": 0.3,
    "pos_sample_prob": 0.15,
    "class_weight_pos_mult": 1.2,
    "label_smoothing": 0.01,
    "grad_accum_steps": 4,
    "train_batch_size": 4,
    "val_batch_size": 4,
    "val_clip_mode": "random",
    "val_n_views": 11
  },
  "slowfast_r50_v2_pretrained": {
    "backbone": "slowfast_r50_v2",
    "backend": "frames",
    "auto_load_best_after_train": true,
    "adamw_weight_decay": 0.0005,
    "grad_clip": 1.0,
    "onecycle_div_factor": 25.0,
    "onecycle_final_div": 10000.0,
    "enable_cb_loss": false,
    "slowfast_alpha": 4,
    "slowfast_fused_dim": 2304,
    "slowfast_hub_model": "slowfast_r50",
    "slowfast_use_pretrained": true,
    "bilstm_hidden": 256,
    "bilstm_layers": 2,
    "use_trivial_aug_wide": false,
    "strong_aug": false,
    "temporal_coherent_aug": true,
    "tc_aug_scale_min": 0.75,
    "tc_aug_color_jitter": 0.1,
    "tc_aug_hflip_prob": 0.5,
    "tc_aug_erasing_prob": 0.1,
    "frame_step": 1,
    "epochs": 20,
    "base_lr": 3e-05,
    "backbone_lr_mult": 0.1,
    "onecycle_peak_mult": 4.0,
    "onecycle_pct_start": 0.25,
    "pos_sample_prob": 0.1,
    "class_weight_pos_mult": 1.2,
    "label_smoothing": 0.02,
    "grad_accum_steps": 4,
    "train_batch_size": 4,
    "val_batch_size": 4,
    "val_clip_mode": "random",
    "val_n_views": 11
  },
  "slowfast_r50_v2_push": {
    "backbone": "slowfast_r50_v2",
    "backend": "frames",
    "auto_load_best_after_train": true,
    "adamw_weight_decay": 0.0005,
    "grad_clip": 1.0,
    "onecycle_div_factor": 25.0,
    "onecycle_final_div": 10000.0,
    "enable_cb_loss": false,
    "slowfast_alpha": 4,
    "slowfast_fused_dim": 2304,
    "slowfast_hub_model": "slowfast_r50",
    "slowfast_use_pretrained": true,
    "bilstm_hidden": 256,
    "bilstm_layers": 2,
    "use_trivial_aug_wide": false,
    "strong_aug": false,
    "temporal_coherent_aug": true,
    "tc_aug_scale_min": 0.75,
    "tc_aug_color_jitter": 0.1,
    "tc_aug_hflip_prob": 0.5,
    "tc_aug_erasing_prob": 0.1,
    "frame_step": 1,
    "epochs": 25,
    "base_lr": 4e-05,
    "backbone_lr_mult": 0.15,
    "onecycle_peak_mult": 5.0,
    "onecycle_pct_start": 0.3,
    "pos_sample_prob": 0.15,
    "class_weight_pos_mult": 1.3,
    "label_smoothing": 0.01,
    "grad_accum_steps": 4,
    "train_batch_size": 4,
    "val_batch_size": 4,
    "val_clip_mode": "random",
    "val_n_views": 11,
    "loss_type": "focal",
    "focal_gamma": 1.2
  },
  "slowfast_r50_v2_nopre": {
    "backbone": "slowfast_r50_v2",
    "backend": "frames",
    "auto_load_best_after_train": true,
    "adamw_weight_decay": 0.0005,
    "grad_clip": 1.0,
    "onecycle_div_factor": 25.0,
    "onecycle_final_div": 10000.0,
    "enable_cb_loss": false,
    "slowfast_alpha": 4,
    "slowfast_fused_dim": 2304,
    "slowfast_hub_model": "slowfast_r50",
    "slowfast_use_pretrained": false,
    "bilstm_hidden": 256,
    "bilstm_layers": 2,
    "use_trivial_aug_wide": false,
    "strong_aug": false,
    "temporal_coherent_aug": true,
    "tc_aug_scale_min": 0.75,
    "tc_aug_color_jitter": 0.1,
    "tc_aug_hflip_prob": 0.5,
    "tc_aug_erasing_prob": 0.1,
    "backbone_lr_mult": 1.0,
    "frame_step": 1,
    "epochs": 30,
    "base_lr": 0.0001,
    "onecycle_peak_mult": 6.0,
    "onecycle_pct_start": 0.3,
    "pos_sample_prob": 0.2,
    "class_weight_pos_mult": 1.5,
    "label_smoothing": 0.0,
    "grad_accum_steps": 4,
    "train_batch_size": 4,
    "val_batch_size": 4,
    "val_clip_mode": "random",
    "val_n_views": 11,
    "loss_type": "focal",
    "focal_gamma": 1.5
  },
  "videomae_crime_v2_conservative": {
    "backbone": "videomae_crime_init_v2",
    "backend": "frames",
    "auto_load_best_after_train": true,
    "adamw_weight_decay": 0.0001,
    "grad_clip": 1.0,
    "onecycle_div_factor": 25.0,
    "onecycle_final_div": 10000.0,
    "enable_cb_loss": false,
    "videomae_crime_grad_checkpointing": true,
    "videomae_crime_model_name": "Nikeytas/videomae-crime-detector-production-v1",
    "bilstm_hidden": 256,
    "bilstm_layers": 2,
    "use_trivial_aug_wide": false,
    "strong_aug": false,
    "temporal_coherent_aug": true,
    "tc_aug_scale_min": 0.8,
    "tc_aug_color_jitter": 0.08,
    "tc_aug_hflip_prob": 0.5,
    "tc_aug_erasing_prob": 0.08,
    "frame_step": 2,
    "epochs": 16,
    "base_lr": 2e-05,
    "backbone_lr_mult": 0.05,
    "onecycle_peak_mult": 3.0,
    "onecycle_pct_start": 0.3,
    "pos_sample_prob": 0.08,
    "class_weight_pos_mult": 1.15,
    "label_smoothing": 0.02,
    "grad_accum_steps": 4,
    "train_batch_size": 4,
    "val_batch_size": 4,
    "val_clip_mode": "random",
    "val_n_views": 11,
    "layer_decay": 0.85
  },
  "videomae_crime_v2_push": {
    "backbone": "videomae_crime_init_v2",
    "backend": "frames",
    "auto_load_best_after_train": true,
    "adamw_weight_decay": 0.0001,
    "grad_clip": 1.0,
    "onecycle_div_factor": 25.0,
    "onecycle_final_div": 10000.0,
    "enable_cb_loss": false,
    "videomae_crime_grad_checkpointing": true,
    "videomae_crime_model_name": "Nikeytas/videomae-crime-detector-production-v1",
    "bilstm_hidden": 256,
    "bilstm_layers": 2,
    "use_trivial_aug_wide": false,
    "strong_aug": false,
    "temporal_coherent_aug": true,
    "tc_aug_scale_min": 0.8,
    "tc_aug_color_jitter": 0.08,
    "tc_aug_hflip_prob": 0.5,
    "tc_aug_erasing_prob": 0.08,
    "frame_step": 2,
    "epochs": 22,
    "base_lr": 3e-05,
    "backbone_lr_mult": 0.1,
    "onecycle_peak_mult": 4.0,
    "onecycle_pct_start": 0.25,
    "pos_sample_prob": 0.12,
    "class_weight_pos_mult": 1.2,
    "label_smoothing": 0.0,
    "grad_accum_steps": 4,
    "train_batch_size": 4,
    "val_batch_size": 4,
    "val_clip_mode": "random",
    "val_n_views": 11,
    "layer_decay": 0.8
  },
  "swin_v2_improved": {
    "backbone": "video_swin_tiny",
    "backend": "frames",
    "auto_load_best_after_train": true,
    "adamw_weight_decay": 0.0005,
    "grad_clip": 1.0,
    "onecycle_div_factor": 25.0,
    "onecycle_final_div": 10000.0,
    "base_lr": 9e-05,
    "backbone_lr_mult": 0.1,
    "onecycle_peak_mult": 8.0,
    "onecycle_pct_start": 0.2,
    "frame_step": 1,
    "epochs": 16,
    "layer_decay": 0.85,
    "enable_cb_loss": true,
    "cb_beta": 0.9995,
    "cb_pos_extra_mult": 1.05,
    "class_weight_pos_mult": 1.1,
    "label_smoothing": 0.02,
    "pos_sample_prob": 0.08,
    "grad_accum_steps": 3,
    "train_batch_size": 7,
    "val_batch_size": 8,
    "val_clip_mode": "random",
    "val_n_views": 11,
    "use_trivial_aug_wide": true,
    "trivial_aug_num_magnitude_bins": 31,
    "strong_aug": false,
    "temporal_coherent_aug": false
  },
  "videomae_small_v2_improved": {
    "backbone": "videomae_small",
    "backend": "frames",
    "auto_load_best_after_train": true,
    "adamw_weight_decay": 0.0001,
    "grad_clip": 1.0,
    "onecycle_div_factor": 25.0,
    "onecycle_final_div": 10000.0,
    "base_lr": 2e-05,
    "backbone_lr_mult": 0.12,
    "onecycle_peak_mult": 3.0,
    "onecycle_pct_start": 0.25,
    "frame_step": 1,
    "epochs": 20,
    "layer_decay": 0.8,
    "enable_cb_loss": true,
    "cb_beta": 0.9997,
    "cb_pos_extra_mult": 1.03,
    "class_weight_pos_mult": 1.15,
    "label_smoothing": 0.0,
    "pos_sample_prob": 0.1,
    "grad_accum_steps": 6,
    "train_batch_size": 2,
    "val_batch_size": 8,
    "val_clip_mode": "random",
    "val_n_views": 11,
    "use_trivial_aug_wide": false,
    "strong_aug": false,
    "temporal_coherent_aug": true,
    "tc_aug_scale_min": 0.8,
    "tc_aug_color_jitter": 0.08
  },
  "convnext_tiny_bilstm": {
    "backbone": "convnext_tiny_bilstm",
    "backend": "frames",
    "auto_load_best_after_train": true,
    "epochs": 15,
    "frame_step": 2,
    "base_lr": 6e-05,
    "backbone_lr_mult": 0.15,
    "adamw_weight_decay": 0.0005,
    "onecycle_peak_mult": 6.0,
    "onecycle_pct_start": 0.25,
    "onecycle_div_factor": 25.0,
    "onecycle_final_div": 10000.0,
    "pos_sample_prob": 0.1,
    "class_weight_pos_mult": 1.15,
    "grad_accum_steps": 4,
    "grad_clip": 1.0,
    "label_smoothing": 0.02,
    "train_batch_size": 4,
    "val_batch_size": 8,
    "val_clip_mode": "random",
    "val_n_views": 11,
    "use_trivial_aug_wide": true,
    "trivial_aug_num_magnitude_bins": 31,
    "strong_aug": false,
    "temporal_coherent_aug": false,
    "enable_cb_loss": false,
    "layer_decay": 1.0,
    "bilstm_hidden": 256,
    "bilstm_layers": 2
  },
  "convnext_base_bilstm": {
    "backbone": "convnext_base_bilstm",
    "backend": "frames",
    "auto_load_best_after_train": true,
    "epochs": 15,
    "frame_step": 2,
    "base_lr": 4e-05,
    "backbone_lr_mult": 0.1,
    "adamw_weight_decay": 0.0005,
    "onecycle_peak_mult": 6.0,
    "onecycle_pct_start": 0.25,
    "onecycle_div_factor": 25.0,
    "onecycle_final_div": 10000.0,
    "pos_sample_prob": 0.1,
    "class_weight_pos_mult": 1.15,
    "grad_accum_steps": 8,
    "grad_clip": 1.0,
    "label_smoothing": 0.02,
    "train_batch_size": 2,
    "val_batch_size": 8,
    "val_clip_mode": "random",
    "val_n_views": 11,
    "use_trivial_aug_wide": true,
    "trivial_aug_num_magnitude_bins": 31,
    "strong_aug": false,
    "temporal_coherent_aug": false,
    "enable_cb_loss": false,
    "layer_decay": 1.0,
    "bilstm_hidden": 256,
    "bilstm_layers": 2
  },
  "efficientnet_b3_bilstm": {
    "backbone": "efficientnet_b3_bilstm",
    "backend": "frames",
    "auto_load_best_after_train": true,
    "epochs": 12,
    "frame_step": 2,
    "base_lr": 7e-05,
    "backbone_lr_mult": 0.2,
    "adamw_weight_decay": 0.0005,
    "onecycle_peak_mult": 6.0,
    "onecycle_pct_start": 0.25,
    "onecycle_div_factor": 25.0,
    "onecycle_final_div": 10000.0,
    "pos_sample_prob": 0.1,
    "class_weight_pos_mult": 1.15,
    "grad_accum_steps": 4,
    "grad_clip": 1.0,
    "label_smoothing": 0.02,
    "train_batch_size": 4,
    "val_batch_size": 8,
    "val_clip_mode": "random",
    "val_n_views": 11,
    "use_trivial_aug_wide": true,
    "trivial_aug_num_magnitude_bins": 31,
    "strong_aug": false,
    "temporal_coherent_aug": false,
    "enable_cb_loss": false,
    "layer_decay": 1.0,
    "bilstm_hidden": 256,
    "bilstm_layers": 2
  },
  "i3d_r50_v2": {
    "backbone": "i3d_r50_v2",
    "backend": "frames",
    "auto_load_best_after_train": true,
    "epochs": 20,
    "frame_step": 1,
    "base_lr": 4e-05,
    "backbone_lr_mult": 0.1,
    "adamw_weight_decay": 0.0005,
    "onecycle_peak_mult": 5.0,
    "onecycle_pct_start": 0.25,
    "onecycle_div_factor": 25.0,
    "onecycle_final_div": 10000.0,
    "pos_sample_prob": 0.1,
    "class_weight_pos_mult": 1.15,
    "grad_accum_steps": 4,
    "grad_clip": 1.0,
    "label_smoothing": 0.02,
    "train_batch_size": 4,
    "val_batch_size": 4,
    "val_clip_mode": "random",
    "val_n_views": 11,
    "use_trivial_aug_wide": false,
    "strong_aug": false,
    "temporal_coherent_aug": true,
    "tc_aug_scale_min": 0.75,
    "tc_aug_color_jitter": 0.1,
    "tc_aug_hflip_prob": 0.5,
    "tc_aug_erasing_prob": 0.1,
    "enable_cb_loss": false,
    "bilstm_hidden": 256,
    "bilstm_layers": 2,
    "i3d_feat_dim": 2048
  },
  "videomae_base_bilstm": {
    "backbone": "videomae_base_bilstm",
    "backend": "frames",
    "auto_load_best_after_train": true,
    "epochs": 16,
    "frame_step": 2,
    "base_lr": 2e-05,
    "backbone_lr_mult": 0.08,
    "adamw_weight_decay": 0.0001,
    "onecycle_peak_mult": 3.0,
    "onecycle_pct_start": 0.3,
    "onecycle_div_factor": 25.0,
    "onecycle_final_div": 10000.0,
    "pos_sample_prob": 0.1,
    "class_weight_pos_mult": 1.15,
    "grad_accum_steps": 6,
    "grad_clip": 1.0,
    "label_smoothing": 0.02,
    "train_batch_size": 2,
    "val_batch_size": 4,
    "val_clip_mode": "random",
    "val_n_views": 11,
    "use_trivial_aug_wide": false,
    "strong_aug": false,
    "temporal_coherent_aug": true,
    "tc_aug_scale_min": 0.8,
    "tc_aug_color_jitter": 0.08,
    "enable_cb_loss": false,
    "layer_decay": 0.85,
    "bilstm_hidden": 256,
    "bilstm_layers": 2,
    "videomae_grad_checkpointing": true
  },
  "videomaev2_base_bilstm": {
    "backbone": "videomaev2_base_bilstm",
    "backend": "frames",
    "auto_load_best_after_train": true,
    "epochs": 18,
    "frame_step": 2,
    "base_lr": 2e-05,
    "backbone_lr_mult": 0.06,
    "adamw_weight_decay": 0.0001,
    "onecycle_peak_mult": 3.0,
    "onecycle_pct_start": 0.3,
    "onecycle_div_factor": 25.0,
    "onecycle_final_div": 10000.0,
    "pos_sample_prob": 0.1,
    "class_weight_pos_mult": 1.15,
    "grad_accum_steps": 6,
    "grad_clip": 1.0,
    "label_smoothing": 0.02,
    "train_batch_size": 2,
    "val_batch_size": 4,
    "val_clip_mode": "random",
    "val_n_views": 11,
    "use_trivial_aug_wide": false,
    "strong_aug": false,
    "temporal_coherent_aug": true,
    "tc_aug_scale_min": 0.8,
    "tc_aug_color_jitter": 0.08,
    "enable_cb_loss": false,
    "layer_decay": 0.85,
    "bilstm_hidden": 256,
    "bilstm_layers": 2,
    "videomae_grad_checkpointing": true
  },
  "convnext_tiny_transformer": {
    "backend": "frames",
    "auto_load_best_after_train": true,
    "adamw_weight_decay": 0.0005,
    "grad_clip": 1.0,
    "onecycle_div_factor": 25.0,
    "onecycle_final_div": 10000.0,
    "pos_sample_prob": 0.1,
    "class_weight_pos_mult": 1.15,
    "grad_accum_steps": 4,
    "train_batch_size": 4,
    "val_batch_size": 8,
    "val_clip_mode": "random",
    "val_n_views": 11,
    "use_trivial_aug_wide": true,
    "trivial_aug_num_magnitude_bins": 31,
    "strong_aug": false,
    "temporal_coherent_aug": false,
    "enable_cb_loss": false,
    "layer_decay": 1.0,
    "bilstm_hidden": 256,
    "bilstm_layers": 2,
    "backbone": "convnext_tiny_transformer",
    "epochs": 18,
    "frame_step": 2,
    "base_lr": 6e-05,
    "backbone_lr_mult": 0.15,
    "onecycle_peak_mult": 6.0,
    "onecycle_pct_start": 0.25,
    "label_smoothing": 0.02,
    "transformer_d_model": 256,
    "transformer_nhead": 4,
    "transformer_layers": 3
  },
  "efficientnet_b0_transformer": {
    "backend": "frames",
    "auto_load_best_after_train": true,
    "adamw_weight_decay": 0.0005,
    "grad_clip": 1.0,
    "onecycle_div_factor": 25.0,
    "onecycle_final_div": 10000.0,
    "pos_sample_prob": 0.1,
    "class_weight_pos_mult": 1.15,
    "grad_accum_steps": 4,
    "train_batch_size": 4,
    "val_batch_size": 8,
    "val_clip_mode": "random",
    "val_n_views": 11,
    "use_trivial_aug_wide": true,
    "trivial_aug_num_magnitude_bins": 31,
    "strong_aug": false,
    "temporal_coherent_aug": false,
    "enable_cb_loss": false,
    "layer_decay": 1.0,
    "bilstm_hidden": 256,
    "bilstm_layers": 2,
    "backbone": "efficientnet_b0_transformer",
    "epochs": 15,
    "frame_step": 2,
    "base_lr": 8e-05,
    "backbone_lr_mult": 0.2,
    "onecycle_peak_mult": 6.0,
    "onecycle_pct_start": 0.25,
    "label_smoothing": 0.0,
    "transformer_d_model": 256,
    "transformer_nhead": 4,
    "transformer_layers": 2
  },
  "convnext_tiny_clip32": {
    "backend": "frames",
    "auto_load_best_after_train": true,
    "adamw_weight_decay": 0.0005,
    "grad_clip": 1.0,
    "onecycle_div_factor": 25.0,
    "onecycle_final_div": 10000.0,
    "pos_sample_prob": 0.1,
    "class_weight_pos_mult": 1.15,
    "grad_accum_steps": 8,
    "train_batch_size": 2,
    "val_batch_size": 8,
    "val_clip_mode": "random",
    "val_n_views": 11,
    "use_trivial_aug_wide": true,
    "trivial_aug_num_magnitude_bins": 31,
    "strong_aug": false,
    "temporal_coherent_aug": false,
    "enable_cb_loss": false,
    "layer_decay": 1.0,
    "bilstm_hidden": 256,
    "bilstm_layers": 2,
    "backbone": "convnext_tiny_bilstm",
    "epochs": 15,
    "frame_step": 2,
    "clip_len": 32,
    "base_lr": 5e-05,
    "backbone_lr_mult": 0.15,
    "onecycle_peak_mult": 6.0,
    "onecycle_pct_start": 0.25,
    "label_smoothing": 0.02
  },
  "efficientnet_b0_clip32": {
    "backend": "frames",
    "auto_load_best_after_train": true,
    "adamw_weight_decay": 0.0005,
    "grad_clip": 1.0,
    "onecycle_div_factor": 25.0,
    "onecycle_final_div": 10000.0,
    "pos_sample_prob": 0.1,
    "class_weight_pos_mult": 1.15,
    "grad_accum_steps": 8,
    "train_batch_size": 2,
    "val_batch_size": 8,
    "val_clip_mode": "random",
    "val_n_views": 11,
    "use_trivial_aug_wide": true,
    "trivial_aug_num_magnitude_bins": 31,
    "strong_aug": false,
    "temporal_coherent_aug": false,
    "enable_cb_loss": false,
    "layer_decay": 1.0,
    "bilstm_hidden": 256,
    "bilstm_layers": 2,
    "backbone": "efficientnet_b0_bilstm",
    "epochs": 12,
    "frame_step": 2,
    "clip_len": 32,
    "base_lr": 7e-05,
    "backbone_lr_mult": 0.2,
    "onecycle_peak_mult": 6.0,
    "onecycle_pct_start": 0.25,
    "label_smoothing": 0.0
  },
  "convnext_tiny_multiscale": {
    "backend": "frames",
    "auto_load_best_after_train": true,
    "adamw_weight_decay": 0.0005,
    "grad_clip": 1.0,
    "onecycle_div_factor": 25.0,
    "onecycle_final_div": 10000.0,
    "pos_sample_prob": 0.1,
    "class_weight_pos_mult": 1.15,
    "grad_accum_steps": 4,
    "train_batch_size": 4,
    "val_batch_size": 8,
    "val_clip_mode": "random",
    "val_n_views": 11,
    "use_trivial_aug_wide": true,
    "trivial_aug_num_magnitude_bins": 31,
    "strong_aug": false,
    "temporal_coherent_aug": false,
    "enable_cb_loss": false,
    "layer_decay": 1.0,
    "bilstm_hidden": 256,
    "bilstm_layers": 2,
    "backbone": "convnext_tiny_multiscale",
    "epochs": 18,
    "frame_step": 2,
    "base_lr": 6e-05,
    "backbone_lr_mult": 0.15,
    "onecycle_peak_mult": 6.0,
    "onecycle_pct_start": 0.25,
    "label_smoothing": 0.02
  },
  "efficientnet_b0_multiscale": {
    "backend": "frames",
    "auto_load_best_after_train": true,
    "adamw_weight_decay": 0.0005,
    "grad_clip": 1.0,
    "onecycle_div_factor": 25.0,
    "onecycle_final_div": 10000.0,
    "pos_sample_prob": 0.1,
    "class_weight_pos_mult": 1.15,
    "grad_accum_steps": 4,
    "train_batch_size": 4,
    "val_batch_size": 8,
    "val_clip_mode": "random",
    "val_n_views": 11,
    "use_trivial_aug_wide": true,
    "trivial_aug_num_magnitude_bins": 31,
    "strong_aug": false,
    "temporal_coherent_aug": false,
    "enable_cb_loss": false,
    "layer_decay": 1.0,
    "bilstm_hidden": 256,
    "bilstm_layers": 2,
    "backbone": "efficientnet_b0_multiscale",
    "epochs": 15,
    "frame_step": 2,
    "base_lr": 8e-05,
    "backbone_lr_mult": 0.2,
    "onecycle_peak_mult": 6.0,
    "onecycle_pct_start": 0.25,
    "label_smoothing": 0.0
  },
  "convnext_tiny_crf": {
    "backend": "frames",
    "auto_load_best_after_train": true,
    "adamw_weight_decay": 0.0005,
    "grad_clip": 1.0,
    "onecycle_div_factor": 25.0,
    "onecycle_final_div": 10000.0,
    "pos_sample_prob": 0.1,
    "class_weight_pos_mult": 1.15,
    "grad_accum_steps": 4,
    "train_batch_size": 4,
    "val_batch_size": 8,
    "val_clip_mode": "random",
    "val_n_views": 11,
    "use_trivial_aug_wide": true,
    "trivial_aug_num_magnitude_bins": 31,
    "strong_aug": false,
    "temporal_coherent_aug": false,
    "enable_cb_loss": false,
    "layer_decay": 1.0,
    "bilstm_hidden": 256,
    "bilstm_layers": 2,
    "backbone": "convnext_tiny_crf",
    "epochs": 18,
    "frame_step": 2,
    "base_lr": 6e-05,
    "backbone_lr_mult": 0.15,
    "onecycle_peak_mult": 6.0,
    "onecycle_pct_start": 0.25,
    "label_smoothing": 0.0,
    "use_crf_loss": true,
    "crf_loss_weight": 0.3
  },
  "efficientnet_b0_crf": {
    "backend": "frames",
    "auto_load_best_after_train": true,
    "adamw_weight_decay": 0.0005,
    "grad_clip": 1.0,
    "onecycle_div_factor": 25.0,
    "onecycle_final_div": 10000.0,
    "pos_sample_prob": 0.1,
    "class_weight_pos_mult": 1.15,
    "grad_accum_steps": 4,
    "train_batch_size": 4,
    "val_batch_size": 8,
    "val_clip_mode": "random",
    "val_n_views": 11,
    "use_trivial_aug_wide": true,
    "trivial_aug_num_magnitude_bins": 31,
    "strong_aug": false,
    "temporal_coherent_aug": false,
    "enable_cb_loss": false,
    "layer_decay": 1.0,
    "bilstm_hidden": 256,
    "bilstm_layers": 2,
    "backbone": "efficientnet_b0_crf",
    "epochs": 15,
    "frame_step": 2,
    "base_lr": 8e-05,
    "backbone_lr_mult": 0.2,
    "onecycle_peak_mult": 6.0,
    "onecycle_pct_start": 0.25,
    "label_smoothing": 0.0,
    "use_crf_loss": true,
    "crf_loss_weight": 0.3
  },
  "convnext_tiny_boundary": {
    "backend": "frames",
    "auto_load_best_after_train": true,
    "adamw_weight_decay": 0.0005,
    "grad_clip": 1.0,
    "onecycle_div_factor": 25.0,
    "onecycle_final_div": 10000.0,
    "pos_sample_prob": 0.1,
    "class_weight_pos_mult": 1.15,
    "grad_accum_steps": 4,
    "train_batch_size": 4,
    "val_batch_size": 8,
    "val_clip_mode": "random",
    "val_n_views": 11,
    "use_trivial_aug_wide": true,
    "trivial_aug_num_magnitude_bins": 31,
    "strong_aug": false,
    "temporal_coherent_aug": false,
    "enable_cb_loss": false,
    "layer_decay": 1.0,
    "bilstm_hidden": 256,
    "bilstm_layers": 2,
    "backbone": "convnext_tiny_bilstm",
    "epochs": 18,
    "frame_step": 2,
    "base_lr": 6e-05,
    "backbone_lr_mult": 0.15,
    "onecycle_peak_mult": 6.0,
    "onecycle_pct_start": 0.25,
    "label_smoothing": 0.02,
    "use_boundary_loss": true,
    "boundary_weight": 2.0,
    "boundary_radius": 3
  },
  "efficientnet_b0_boundary": {
    "backend": "frames",
    "auto_load_best_after_train": true,
    "adamw_weight_decay": 0.0005,
    "grad_clip": 1.0,
    "onecycle_div_factor": 25.0,
    "onecycle_final_div": 10000.0,
    "pos_sample_prob": 0.1,
    "class_weight_pos_mult": 1.15,
    "grad_accum_steps": 4,
    "train_batch_size": 4,
    "val_batch_size": 8,
    "val_clip_mode": "random",
    "val_n_views": 11,
    "use_trivial_aug_wide": true,
    "trivial_aug_num_magnitude_bins": 31,
    "strong_aug": false,
    "temporal_coherent_aug": false,
    "enable_cb_loss": false,
    "layer_decay": 1.0,
    "bilstm_hidden": 256,
    "bilstm_layers": 2,
    "backbone": "efficientnet_b0_bilstm",
    "epochs": 15,
    "frame_step": 2,
    "base_lr": 8e-05,
    "backbone_lr_mult": 0.2,
    "onecycle_peak_mult": 6.0,
    "onecycle_pct_start": 0.25,
    "label_smoothing": 0.0,
    "use_boundary_loss": true,
    "boundary_weight": 2.0,
    "boundary_radius": 3
  },
  "convnext_tiny_skeleton": {
    "backend": "frames",
    "auto_load_best_after_train": true,
    "adamw_weight_decay": 0.0005,
    "grad_clip": 1.0,
    "onecycle_div_factor": 25.0,
    "onecycle_final_div": 10000.0,
    "pos_sample_prob": 0.1,
    "class_weight_pos_mult": 1.15,
    "grad_accum_steps": 4,
    "train_batch_size": 4,
    "val_batch_size": 8,
    "val_clip_mode": "random",
    "val_n_views": 11,
    "use_trivial_aug_wide": true,
    "trivial_aug_num_magnitude_bins": 31,
    "strong_aug": false,
    "temporal_coherent_aug": false,
    "enable_cb_loss": false,
    "layer_decay": 1.0,
    "bilstm_hidden": 256,
    "bilstm_layers": 2,
    "backbone": "convnext_tiny_skeleton",
    "epochs": 18,
    "frame_step": 2,
    "base_lr": 6e-05,
    "backbone_lr_mult": 0.15,
    "onecycle_peak_mult": 6.0,
    "onecycle_pct_start": 0.25,
    "label_smoothing": 0.02,
    "skeleton_dim": 406,
    "use_skeleton": true
  },
  "convnext_tiny_flow": {
    "backend": "frames",
    "auto_load_best_after_train": true,
    "adamw_weight_decay": 0.0005,
    "grad_clip": 1.0,
    "onecycle_div_factor": 25.0,
    "onecycle_final_div": 10000.0,
    "pos_sample_prob": 0.1,
    "class_weight_pos_mult": 1.15,
    "grad_accum_steps": 8,
    "train_batch_size": 2,
    "val_batch_size": 8,
    "val_clip_mode": "random",
    "val_n_views": 11,
    "use_trivial_aug_wide": true,
    "trivial_aug_num_magnitude_bins": 31,
    "strong_aug": false,
    "temporal_coherent_aug": false,
    "enable_cb_loss": false,
    "layer_decay": 1.0,
    "bilstm_hidden": 256,
    "bilstm_layers": 2,
    "backbone": "convnext_tiny_flow",
    "epochs": 18,
    "frame_step": 2,
    "base_lr": 5e-05,
    "backbone_lr_mult": 0.12,
    "onecycle_peak_mult": 5.0,
    "onecycle_pct_start": 0.25,
    "label_smoothing": 0.02,
    "flow_backbone": "efficientnet_b0"
  },
  "convnext_tiny_focal_clip32": {
    "backend": "frames",
    "auto_load_best_after_train": true,
    "epochs": 18,
    "clip_len": 32,
    "frame_step": 2,
    "base_lr": 6e-05,
    "backbone_lr_mult": 0.15,
    "adamw_weight_decay": 0.0005,
    "onecycle_peak_mult": 6.0,
    "onecycle_pct_start": 0.25,
    "onecycle_div_factor": 25.0,
    "onecycle_final_div": 10000.0,
    "pos_sample_prob": 0.1,
    "class_weight_pos_mult": 1.15,
    "grad_accum_steps": 8,
    "grad_clip": 1.0,
    "label_smoothing": 0.0,
    "train_batch_size": 2,
    "val_batch_size": 8,
    "val_clip_mode": "random",
    "val_n_views": 11,
    "use_trivial_aug_wide": true,
    "trivial_aug_num_magnitude_bins": 31,
    "strong_aug": false,
    "temporal_coherent_aug": false,
    "enable_cb_loss": false,
    "layer_decay": 1.0,
    "bilstm_hidden": 256,
    "bilstm_layers": 2,
    "use_boundary_loss": true,
    "boundary_weight": 2.0,
    "boundary_radius": 3,
    "backbone": "convnext_tiny_bilstm",
    "loss_type": "focal",
    "focal_gamma": 2.0
  },
  "convnext_tiny_highpos_clip32": {
    "backend": "frames",
    "auto_load_best_after_train": true,
    "epochs": 18,
    "clip_len": 32,
    "frame_step": 2,
    "base_lr": 6e-05,
    "backbone_lr_mult": 0.15,
    "adamw_weight_decay": 0.0005,
    "onecycle_peak_mult": 6.0,
    "onecycle_pct_start": 0.25,
    "onecycle_div_factor": 25.0,
    "onecycle_final_div": 10000.0,
    "pos_sample_prob": 0.25,
    "class_weight_pos_mult": 1.15,
    "grad_accum_steps": 8,
    "grad_clip": 1.0,
    "label_smoothing": 0.02,
    "train_batch_size": 2,
    "val_batch_size": 8,
    "val_clip_mode": "random",
    "val_n_views": 11,
    "use_trivial_aug_wide": true,
    "trivial_aug_num_magnitude_bins": 31,
    "strong_aug": false,
    "temporal_coherent_aug": false,
    "enable_cb_loss": false,
    "layer_decay": 1.0,
    "bilstm_hidden": 256,
    "bilstm_layers": 2,
    "use_boundary_loss": true,
    "boundary_weight": 2.0,
    "boundary_radius": 3,
    "backbone": "convnext_tiny_bilstm"
  },
  "convnext_small_boundary_clip32": {
    "backend": "frames",
    "auto_load_best_after_train": true,
    "epochs": 18,
    "clip_len": 32,
    "frame_step": 2,
    "base_lr": 5e-05,
    "backbone_lr_mult": 0.12,
    "adamw_weight_decay": 0.0005,
    "onecycle_peak_mult": 6.0,
    "onecycle_pct_start": 0.25,
    "onecycle_div_factor": 25.0,
    "onecycle_final_div": 10000.0,
    "pos_sample_prob": 0.1,
    "class_weight_pos_mult": 1.15,
    "grad_accum_steps": 8,
    "grad_clip": 1.0,
    "label_smoothing": 0.02,
    "train_batch_size": 2,
    "val_batch_size": 8,
    "val_clip_mode": "random",
    "val_n_views": 11,
    "use_trivial_aug_wide": true,
    "trivial_aug_num_magnitude_bins": 31,
    "strong_aug": false,
    "temporal_coherent_aug": false,
    "enable_cb_loss": false,
    "layer_decay": 1.0,
    "bilstm_hidden": 256,
    "bilstm_layers": 2,
    "use_boundary_loss": true,
    "boundary_weight": 2.0,
    "boundary_radius": 3,
    "backbone": "convnext_small_bilstm"
  },
  "convnext_tiny_tcn_clip32": {
    "backend": "frames",
    "auto_load_best_after_train": true,
    "epochs": 18,
    "clip_len": 32,
    "frame_step": 2,
    "base_lr": 6e-05,
    "backbone_lr_mult": 0.15,
    "adamw_weight_decay": 0.0005,
    "onecycle_peak_mult": 6.0,
    "onecycle_pct_start": 0.25,
    "onecycle_div_factor": 25.0,
    "onecycle_final_div": 10000.0,
    "pos_sample_prob": 0.1,
    "class_weight_pos_mult": 1.15,
    "grad_accum_steps": 8,
    "grad_clip": 1.0,
    "label_smoothing": 0.02,
    "train_batch_size": 2,
    "val_batch_size": 8,
    "val_clip_mode": "random",
    "val_n_views": 11,
    "use_trivial_aug_wide": true,
    "trivial_aug_num_magnitude_bins": 31,
    "strong_aug": false,
    "temporal_coherent_aug": false,
    "enable_cb_loss": false,
    "layer_decay": 1.0,
    "bilstm_hidden": 256,
    "bilstm_layers": 2,
    "use_boundary_loss": false,
    "boundary_weight": 2.0,
    "boundary_radius": 3,
    "backbone": "convnext_tiny_tcn",
    "tcn_hidden": 256,
    "tcn_layers": 5,
    "tcn_kernel_size": 3
  },
  "convnext_tiny_focal_highpos_clip32": {
    "backend": "frames",
    "auto_load_best_after_train": true,
    "epochs": 18,
    "clip_len": 32,
    "frame_step": 2,
    "base_lr": 6e-05,
    "backbone_lr_mult": 0.15,
    "adamw_weight_decay": 0.0005,
    "onecycle_peak_mult": 6.0,
    "onecycle_pct_start": 0.25,
    "onecycle_div_factor": 25.0,
    "onecycle_final_div": 10000.0,
    "pos_sample_prob": 0.25,
    "class_weight_pos_mult": 1.15,
    "grad_accum_steps": 8,
    "grad_clip": 1.0,
    "label_smoothing": 0.0,
    "train_batch_size": 2,
    "val_batch_size": 8,
    "val_clip_mode": "random",
    "val_n_views": 11,
    "use_trivial_aug_wide": true,
    "trivial_aug_num_magnitude_bins": 31,
    "strong_aug": false,
    "temporal_coherent_aug": false,
    "enable_cb_loss": false,
    "layer_decay": 1.0,
    "bilstm_hidden": 256,
    "bilstm_layers": 2,
    "use_boundary_loss": true,
    "boundary_weight": 2.0,
    "boundary_radius": 3,
    "backbone": "convnext_tiny_bilstm",
    "loss_type": "focal",
    "focal_gamma": 2.0
  },
  "resnet18_best_reference_06626": {
    "backbone": "resnet18",
    "backend": "frames",
    "epochs": 15,
    "frame_step": 2,
    "pos_sample_prob": 0.0,
    "grad_accum_steps": 4,
    "grad_clip": 1.0,
    "amp": true,
    "label_smoothing": 0.05,
    "class_weight_pos_mult": 1.0,
    "resnet_lr": 0.001,
    "resnet_weight_decay": 0.0005,
    "resnet_momentum": 0.9,
    "resnet_nesterov": true,
    "resnet_max_lr": 0.05,
    "resnet_pct_start": 0.1,
    "resnet_base_momentum": 0.85,
    "resnet_max_momentum": 0.95,
    "resnet_div_factor": 25.0,
    "resnet_final_div_factor": 10000.0,
    "auto_load_best_after_train": true
  },
  "convnext_tiny_tcn_boundary_clip32": {
    "backbone": "convnext_tiny_tcn",
    "backend": "frames",
    "auto_load_best_after_train": true,
    "clip_len": 32,
    "epochs": 18,
    "frame_step": 2,
    "base_lr": 6e-05,
    "backbone_lr_mult": 0.15,
    "adamw_weight_decay": 0.0005,
    "onecycle_peak_mult": 6.0,
    "onecycle_pct_start": 0.25,
    "onecycle_div_factor": 25.0,
    "onecycle_final_div": 10000.0,
    "pos_sample_prob": 0.1,
    "class_weight_pos_mult": 1.15,
    "grad_accum_steps": 8,
    "grad_clip": 1.0,
    "label_smoothing": 0.02,
    "train_batch_size": 2,
    "val_batch_size": 8,
    "val_clip_mode": "random",
    "val_n_views": 11,
    "use_trivial_aug_wide": true,
    "trivial_aug_num_magnitude_bins": 31,
    "strong_aug": false,
    "temporal_coherent_aug": false,
    "enable_cb_loss": false,
    "layer_decay": 1.0,
    "tcn_hidden": 256,
    "tcn_layers": 5,
    "tcn_kernel_size": 3,
    "use_boundary_loss": true,
    "boundary_weight": 2.0,
    "boundary_radius": 3
  },
  "convnext_tiny_bilstm_boundary_clip32": {
    "backbone": "convnext_tiny_bilstm",
    "backend": "frames",
    "auto_load_best_after_train": true,
    "clip_len": 32,
    "epochs": 18,
    "frame_step": 2,
    "base_lr": 6e-05,
    "backbone_lr_mult": 0.15,
    "adamw_weight_decay": 0.0005,
    "onecycle_peak_mult": 6.0,
    "onecycle_pct_start": 0.25,
    "onecycle_div_factor": 25.0,
    "onecycle_final_div": 10000.0,
    "pos_sample_prob": 0.1,
    "class_weight_pos_mult": 1.15,
    "grad_accum_steps": 8,
    "grad_clip": 1.0,
    "label_smoothing": 0.02,
    "train_batch_size": 2,
    "val_batch_size": 8,
    "val_clip_mode": "random",
    "val_n_views": 11,
    "use_trivial_aug_wide": true,
    "trivial_aug_num_magnitude_bins": 31,
    "strong_aug": false,
    "temporal_coherent_aug": false,
    "enable_cb_loss": false,
    "layer_decay": 1.0,
    "bilstm_hidden": 256,
    "bilstm_layers": 2,
    "use_boundary_loss": true,
    "boundary_weight": 2.0,
    "boundary_radius": 3
  },
  "skeleton_fusion_bilstm_clip32_frozen_rgb": {
    "backend": "frames",
    "auto_load_best_after_train": true,
    "adamw_weight_decay": 0.0005,
    "grad_clip": 1.0,
    "onecycle_div_factor": 25.0,
    "onecycle_final_div": 10000.0,
    "pos_sample_prob": 0.1,
    "class_weight_pos_mult": 1.15,
    "grad_accum_steps": 8,
    "train_batch_size": 2,
    "val_batch_size": 4,
    "val_clip_mode": "random",
    "val_n_views": 11,
    "use_trivial_aug_wide": true,
    "trivial_aug_num_magnitude_bins": 31,
    "strong_aug": false,
    "temporal_coherent_aug": false,
    "enable_cb_loss": false,
    "layer_decay": 1.0,
    "bilstm_hidden": 256,
    "bilstm_layers": 2,
    "backbone": "skeleton_fusion_bilstm",
    "epochs": 18,
    "frame_step": 2,
    "base_lr": 6e-05,
    "backbone_lr_mult": 0.15,
    "onecycle_peak_mult": 6.0,
    "onecycle_pct_start": 0.25,
    "label_smoothing": 0.02,
    "skeleton_dim": 406,
    "use_skeleton": true,
    "skeleton_root_train": "skeleton/Training",
    "skeleton_root_val": "skeleton/Validation",
    "clip_len": 32,
    "val_amp": true,
    "val_micro_batch_size": 1,
    "rgb_backbone_checkpoint": "runs/convnext_tiny_clip32 0.78/best.pt",
    "freeze_rgb_backbone": true,
    "strict_require_skeleton": true,
    "fusion_dim": 512,
    "fusion_nhead": 4,
    "fuse_dropout": 0.1,
    "_desc": "Skeleton + RGB fusion (BiLSTM, default gated). RGB заморожен из лучшей convnext_tiny_clip32.",
    "skeleton_fusion_type": "gated"
  },
  "skeleton_concat_bilstm_clip32_frozen_rgb": {
    "backend": "frames",
    "auto_load_best_after_train": true,
    "adamw_weight_decay": 0.0005,
    "grad_clip": 1.0,
    "onecycle_div_factor": 25.0,
    "onecycle_final_div": 10000.0,
    "pos_sample_prob": 0.1,
    "class_weight_pos_mult": 1.15,
    "grad_accum_steps": 8,
    "train_batch_size": 2,
    "val_batch_size": 4,
    "val_clip_mode": "random",
    "val_n_views": 11,
    "use_trivial_aug_wide": true,
    "trivial_aug_num_magnitude_bins": 31,
    "strong_aug": false,
    "temporal_coherent_aug": false,
    "enable_cb_loss": false,
    "layer_decay": 1.0,
    "bilstm_hidden": 256,
    "bilstm_layers": 2,
    "backbone": "skeleton_concat_bilstm",
    "epochs": 18,
    "frame_step": 2,
    "base_lr": 6e-05,
    "backbone_lr_mult": 0.15,
    "onecycle_peak_mult": 6.0,
    "onecycle_pct_start": 0.25,
    "label_smoothing": 0.02,
    "skeleton_dim": 406,
    "use_skeleton": true,
    "skeleton_root_train": "skeleton/Training",
    "skeleton_root_val": "skeleton/Validation",
    "clip_len": 32,
    "val_amp": true,
    "val_micro_batch_size": 1,
    "rgb_backbone_checkpoint": "runs/convnext_tiny_clip32 0.78/best.pt",
    "freeze_rgb_backbone": true,
    "strict_require_skeleton": true,
    "fusion_dim": 512,
    "fusion_nhead": 4,
    "fuse_dropout": 0.1,
    "_desc": "Skeleton + RGB concat fusion (BiLSTM). RGB заморожен из лучшей convnext_tiny_clip32.",
    "skeleton_fusion_type": "concat"
  },
  "skeleton_gated_bilstm_clip32_frozen_rgb": {
    "backend": "frames",
    "auto_load_best_after_train": true,
    "adamw_weight_decay": 0.0005,
    "grad_clip": 1.0,
    "onecycle_div_factor": 25.0,
    "onecycle_final_div": 10000.0,
    "pos_sample_prob": 0.1,
    "class_weight_pos_mult": 1.15,
    "grad_accum_steps": 8,
    "train_batch_size": 2,
    "val_batch_size": 4,
    "val_clip_mode": "random",
    "val_n_views": 11,
    "use_trivial_aug_wide": true,
    "trivial_aug_num_magnitude_bins": 31,
    "strong_aug": false,
    "temporal_coherent_aug": false,
    "enable_cb_loss": false,
    "layer_decay": 1.0,
    "bilstm_hidden": 256,
    "bilstm_layers": 2,
    "backbone": "skeleton_gated_bilstm",
    "epochs": 18,
    "frame_step": 2,
    "base_lr": 6e-05,
    "backbone_lr_mult": 0.15,
    "onecycle_peak_mult": 6.0,
    "onecycle_pct_start": 0.25,
    "label_smoothing": 0.02,
    "skeleton_dim": 406,
    "use_skeleton": true,
    "skeleton_root_train": "skeleton/Training",
    "skeleton_root_val": "skeleton/Validation",
    "clip_len": 32,
    "val_amp": true,
    "val_micro_batch_size": 1,
    "rgb_backbone_checkpoint": "runs/convnext_tiny_clip32 0.78/best.pt",
    "freeze_rgb_backbone": true,
    "strict_require_skeleton": true,
    "fusion_dim": 512,
    "fusion_nhead": 4,
    "fuse_dropout": 0.1,
    "_desc": "Skeleton + RGB gated fusion (BiLSTM). RGB заморожен из лучшей convnext_tiny_clip32.",
    "skeleton_fusion_type": "gated"
  },
  "skeleton_attention_bilstm_clip32_frozen_rgb": {
    "backend": "frames",
    "auto_load_best_after_train": true,
    "adamw_weight_decay": 0.0005,
    "grad_clip": 1.0,
    "onecycle_div_factor": 25.0,
    "onecycle_final_div": 10000.0,
    "pos_sample_prob": 0.1,
    "class_weight_pos_mult": 1.15,
    "grad_accum_steps": 8,
    "train_batch_size": 2,
    "val_batch_size": 4,
    "val_clip_mode": "random",
    "val_n_views": 11,
    "use_trivial_aug_wide": true,
    "trivial_aug_num_magnitude_bins": 31,
    "strong_aug": false,
    "temporal_coherent_aug": false,
    "enable_cb_loss": false,
    "layer_decay": 1.0,
    "bilstm_hidden": 256,
    "bilstm_layers": 2,
    "backbone": "skeleton_attention_bilstm",
    "epochs": 18,
    "frame_step": 2,
    "base_lr": 6e-05,
    "backbone_lr_mult": 0.15,
    "onecycle_peak_mult": 6.0,
    "onecycle_pct_start": 0.25,
    "label_smoothing": 0.02,
    "skeleton_dim": 406,
    "use_skeleton": true,
    "skeleton_root_train": "skeleton/Training",
    "skeleton_root_val": "skeleton/Validation",
    "clip_len": 32,
    "val_amp": true,
    "val_micro_batch_size": 1,
    "rgb_backbone_checkpoint": "runs/convnext_tiny_clip32 0.78/best.pt",
    "freeze_rgb_backbone": true,
    "strict_require_skeleton": true,
    "fusion_dim": 512,
    "fusion_nhead": 4,
    "fuse_dropout": 0.1,
    "_desc": "Skeleton + RGB cross-attention fusion (BiLSTM). RGB заморожен из лучшей convnext_tiny_clip32.",
    "skeleton_fusion_type": "attention"
  },
  "skeleton_fusion_tcn_clip32_frozen_rgb": {
    "backend": "frames",
    "auto_load_best_after_train": true,
    "adamw_weight_decay": 0.0005,
    "grad_clip": 1.0,
    "onecycle_div_factor": 25.0,
    "onecycle_final_div": 10000.0,
    "pos_sample_prob": 0.1,
    "class_weight_pos_mult": 1.15,
    "grad_accum_steps": 8,
    "train_batch_size": 2,
    "val_batch_size": 4,
    "val_clip_mode": "random",
    "val_n_views": 11,
    "use_trivial_aug_wide": true,
    "trivial_aug_num_magnitude_bins": 31,
    "strong_aug": false,
    "temporal_coherent_aug": false,
    "enable_cb_loss": false,
    "layer_decay": 1.0,
    "bilstm_hidden": 256,
    "bilstm_layers": 2,
    "backbone": "skeleton_fusion_tcn",
    "epochs": 18,
    "frame_step": 2,
    "base_lr": 6e-05,
    "backbone_lr_mult": 0.15,
    "onecycle_peak_mult": 6.0,
    "onecycle_pct_start": 0.25,
    "label_smoothing": 0.02,
    "skeleton_dim": 406,
    "use_skeleton": true,
    "skeleton_root_train": "skeleton/Training",
    "skeleton_root_val": "skeleton/Validation",
    "clip_len": 32,
    "val_amp": true,
    "val_micro_batch_size": 1,
    "rgb_backbone_checkpoint": "runs/convnext_tiny_clip32 0.78/best.pt",
    "freeze_rgb_backbone": true,
    "strict_require_skeleton": true,
    "fusion_dim": 512,
    "fusion_nhead": 4,
    "fuse_dropout": 0.1,
    "_desc": "Skeleton + RGB fusion (TCN, default gated). RGB заморожен из лучшей convnext_tiny_clip32.",
    "skeleton_fusion_type": "gated"
  },
  "skeleton_concat_tcn_clip32_frozen_rgb": {
    "backend": "frames",
    "auto_load_best_after_train": true,
    "adamw_weight_decay": 0.0005,
    "grad_clip": 1.0,
    "onecycle_div_factor": 25.0,
    "onecycle_final_div": 10000.0,
    "pos_sample_prob": 0.1,
    "class_weight_pos_mult": 1.15,
    "grad_accum_steps": 8,
    "train_batch_size": 2,
    "val_batch_size": 4,
    "val_clip_mode": "random",
    "val_n_views": 11,
    "use_trivial_aug_wide": true,
    "trivial_aug_num_magnitude_bins": 31,
    "strong_aug": false,
    "temporal_coherent_aug": false,
    "enable_cb_loss": false,
    "layer_decay": 1.0,
    "bilstm_hidden": 256,
    "bilstm_layers": 2,
    "backbone": "skeleton_concat_tcn",
    "epochs": 18,
    "frame_step": 2,
    "base_lr": 6e-05,
    "backbone_lr_mult": 0.15,
    "onecycle_peak_mult": 6.0,
    "onecycle_pct_start": 0.25,
    "label_smoothing": 0.02,
    "skeleton_dim": 406,
    "use_skeleton": true,
    "skeleton_root_train": "skeleton/Training",
    "skeleton_root_val": "skeleton/Validation",
    "clip_len": 32,
    "val_amp": true,
    "val_micro_batch_size": 1,
    "rgb_backbone_checkpoint": "runs/convnext_tiny_clip32 0.78/best.pt",
    "freeze_rgb_backbone": true,
    "strict_require_skeleton": true,
    "fusion_dim": 512,
    "fusion_nhead": 4,
    "fuse_dropout": 0.1,
    "_desc": "Skeleton + RGB concat fusion (TCN). RGB заморожен из лучшей convnext_tiny_clip32.",
    "skeleton_fusion_type": "concat"
  },
  "skeleton_gated_tcn_clip32_frozen_rgb": {
    "backend": "frames",
    "auto_load_best_after_train": true,
    "adamw_weight_decay": 0.0005,
    "grad_clip": 1.0,
    "onecycle_div_factor": 25.0,
    "onecycle_final_div": 10000.0,
    "pos_sample_prob": 0.1,
    "class_weight_pos_mult": 1.15,
    "grad_accum_steps": 8,
    "train_batch_size": 2,
    "val_batch_size": 4,
    "val_clip_mode": "random",
    "val_n_views": 11,
    "use_trivial_aug_wide": true,
    "trivial_aug_num_magnitude_bins": 31,
    "strong_aug": false,
    "temporal_coherent_aug": false,
    "enable_cb_loss": false,
    "layer_decay": 1.0,
    "bilstm_hidden": 256,
    "bilstm_layers": 2,
    "backbone": "skeleton_gated_tcn",
    "epochs": 18,
    "frame_step": 2,
    "base_lr": 6e-05,
    "backbone_lr_mult": 0.15,
    "onecycle_peak_mult": 6.0,
    "onecycle_pct_start": 0.25,
    "label_smoothing": 0.02,
    "skeleton_dim": 406,
    "use_skeleton": true,
    "skeleton_root_train": "skeleton/Training",
    "skeleton_root_val": "skeleton/Validation",
    "clip_len": 32,
    "val_amp": true,
    "val_micro_batch_size": 1,
    "rgb_backbone_checkpoint": "runs/convnext_tiny_clip32 0.78/best.pt",
    "freeze_rgb_backbone": true,
    "strict_require_skeleton": true,
    "fusion_dim": 512,
    "fusion_nhead": 4,
    "fuse_dropout": 0.1,
    "_desc": "Skeleton + RGB gated fusion (TCN). RGB заморожен из лучшей convnext_tiny_clip32.",
    "skeleton_fusion_type": "gated"
  },
  "skeleton_attention_tcn_clip32_frozen_rgb": {
    "backend": "frames",
    "auto_load_best_after_train": true,
    "adamw_weight_decay": 0.0005,
    "grad_clip": 1.0,
    "onecycle_div_factor": 25.0,
    "onecycle_final_div": 10000.0,
    "pos_sample_prob": 0.1,
    "class_weight_pos_mult": 1.15,
    "grad_accum_steps": 8,
    "train_batch_size": 2,
    "val_batch_size": 4,
    "val_clip_mode": "random",
    "val_n_views": 11,
    "use_trivial_aug_wide": true,
    "trivial_aug_num_magnitude_bins": 31,
    "strong_aug": false,
    "temporal_coherent_aug": false,
    "enable_cb_loss": false,
    "layer_decay": 1.0,
    "bilstm_hidden": 256,
    "bilstm_layers": 2,
    "backbone": "skeleton_attention_tcn",
    "epochs": 18,
    "frame_step": 2,
    "base_lr": 6e-05,
    "backbone_lr_mult": 0.15,
    "onecycle_peak_mult": 6.0,
    "onecycle_pct_start": 0.25,
    "label_smoothing": 0.02,
    "skeleton_dim": 406,
    "use_skeleton": true,
    "skeleton_root_train": "skeleton/Training",
    "skeleton_root_val": "skeleton/Validation",
    "clip_len": 32,
    "val_amp": true,
    "val_micro_batch_size": 1,
    "rgb_backbone_checkpoint": "runs/convnext_tiny_clip32 0.78/best.pt",
    "freeze_rgb_backbone": true,
    "strict_require_skeleton": true,
    "fusion_dim": 512,
    "fusion_nhead": 4,
    "fuse_dropout": 0.1,
    "_desc": "Skeleton + RGB cross-attention fusion (TCN). RGB заморожен из лучшей convnext_tiny_clip32.",
    "skeleton_fusion_type": "attention"
  }
}
